{
  "id": 274637746,
  "id_str": "274637746",
  "name": "Dmitriy M.",
  "screen_name": "v1sarRU",
  "location": "Russia, Moscow",
  "profile_location": null,
  "description": "Android developer at Revolut",
  "url": null,
  "entities": {
    "description": {
      "urls": []
    }
  },
  "protected": false,
  "followers_count": 45,
  "friends_count": 67,
  "listed_count": 0,
  "created_at": "Wed Mar 30 17:49:39 +0000 2011",
  "favourites_count": 15,
  "utc_offset": null,
  "time_zone": null,
  "geo_enabled": false,
  "verified": false,
  "statuses_count": 66,
  "lang": null,
  "status": {
    "created_at": "Fri Sep 27 17:35:35 +0000 2019",
    "id": 1177637925103849500,
    "id_str": "1177637925103849472",
    "text": "RT @MobiusConf: На Mobius 2019 Piter многие из вас видели доклад от @e_matsyuk и @v1sarRU про автотесты. https://t.co/ONn5uV0IqV\n\nИ совсем…",
    "truncated": false,
    "entities": {
      "hashtags": [],
      "symbols": [],
      "user_mentions": [
        {
          "screen_name": "MobiusConf",
          "name": "Mobius",
          "id": 3027882327,
          "id_str": "3027882327",
          "indices": [3, 14]
        },
        {
          "screen_name": "e_matsyuk",
          "name": "Matzuk",
          "id": 211917597,
          "id_str": "211917597",
          "indices": [68, 78]
        },
        {
          "screen_name": "v1sarRU",
          "name": "Dmitriy M.",
          "id": 274637746,
          "id_str": "274637746",
          "indices": [81, 89]
        }
      ],
      "urls": [
        {
          "url": "https://t.co/ONn5uV0IqV",
          "expanded_url": "https://youtu.be/q_8UUhVDV7c",
          "display_url": "youtu.be/q_8UUhVDV7c",
          "indices": [105, 128]
        }
      ]
    },
    "source": "<a href=\"http://twitter.com/download/android\" rel=\"nofollow\">Twitter for Android</a>",
    "in_reply_to_status_id": null,
    "in_reply_to_status_id_str": null,
    "in_reply_to_user_id": null,
    "in_reply_to_user_id_str": null,
    "in_reply_to_screen_name": null,
    "geo": null,
    "coordinates": null,
    "place": null,
    "contributors": null,
    "retweeted_status": {
      "created_at": "Tue Sep 24 10:17:33 +0000 2019",
      "id": 1176440526658297900,
      "id_str": "1176440526658297857",
      "text": "На Mobius 2019 Piter многие из вас видели доклад от @e_matsyuk и @v1sarRU про автотесты. https://t.co/ONn5uV0IqV\n\nИ… https://t.co/aBferD7cUf",
      "truncated": true,
      "entities": {
        "hashtags": [],
        "symbols": [],
        "user_mentions": [
          {
            "screen_name": "e_matsyuk",
            "name": "Matzuk",
            "id": 211917597,
            "id_str": "211917597",
            "indices": [52, 62]
          },
          {
            "screen_name": "v1sarRU",
            "name": "Dmitriy M.",
            "id": 274637746,
            "id_str": "274637746",
            "indices": [65, 73]
          }
        ],
        "urls": [
          {
            "url": "https://t.co/ONn5uV0IqV",
            "expanded_url": "https://youtu.be/q_8UUhVDV7c",
            "display_url": "youtu.be/q_8UUhVDV7c",
            "indices": [89, 112]
          },
          {
            "url": "https://t.co/aBferD7cUf",
            "expanded_url": "https://twitter.com/i/web/status/1176440526658297857",
            "display_url": "twitter.com/i/web/status/1…",
            "indices": [117, 140]
          }
        ]
      },
      "source": "<a href=\"https://mobile.twitter.com\" rel=\"nofollow\">Twitter Web App</a>",
      "in_reply_to_status_id": null,
      "in_reply_to_status_id_str": null,
      "in_reply_to_user_id": null,
      "in_reply_to_user_id_str": null,
      "in_reply_to_screen_name": null,
      "geo": null,
      "coordinates": null,
      "place": null,
      "contributors": null,
      "is_quote_status": false,
      "retweet_count": 5,
      "favorite_count": 8,
      "favorited": false,
      "retweeted": false,
      "possibly_sensitive": false,
      "lang": "ru"
    },
    "is_quote_status": false,
    "retweet_count": 5,
    "favorite_count": 0,
    "favorited": false,
    "retweeted": false,
    "possibly_sensitive": false,
    "lang": "ru"
  },
  "contributors_enabled": false,
  "is_translator": false,
  "is_translation_enabled": false,
  "profile_background_color": "000000",
  "profile_background_image_url": "http://abs.twimg.com/images/themes/theme1/bg.png",
  "profile_background_image_url_https": "https://abs.twimg.com/images/themes/theme1/bg.png",
  "profile_background_tile": true,
  "profile_image_url": "http://pbs.twimg.com/profile_images/1141682641944682496/G5RefSQF_normal.jpg",
  "profile_image_url_https": "https://pbs.twimg.com/profile_images/1141682641944682496/G5RefSQF_normal.jpg",
  "profile_link_color": "DD5563",
  "profile_sidebar_border_color": "816F46",
  "profile_sidebar_fill_color": "DEDEDE",
  "profile_text_color": "2B0C13",
  "profile_use_background_image": true,
  "has_extended_profile": false,
  "default_profile": false,
  "default_profile_image": false,
  "following": false,
  "follow_request_sent": false,
  "notifications": false,
  "translator_type": "none",
  "geometry": {
    "lat": 0,
    "lng": 0
  }
}
